README.md
setup.py
crowdstrike_pulumi/__init__.py
crowdstrike_pulumi/_inputs.py
crowdstrike_pulumi/_utilities.py
crowdstrike_pulumi/cloud_aws_account.py
crowdstrike_pulumi/default_prevention_policy_linux.py
crowdstrike_pulumi/default_prevention_policy_mac.py
crowdstrike_pulumi/default_prevention_policy_windows.py
crowdstrike_pulumi/default_sensor_update_policy.py
crowdstrike_pulumi/filevantage_policy.py
crowdstrike_pulumi/filevantage_rule_group.py
crowdstrike_pulumi/get_cloud_aws_account.py
crowdstrike_pulumi/get_sensor_update_policy_builds.py
crowdstrike_pulumi/host_group.py
crowdstrike_pulumi/outputs.py
crowdstrike_pulumi/prevention_policy_attachment.py
crowdstrike_pulumi/prevention_policy_linux.py
crowdstrike_pulumi/prevention_policy_mac.py
crowdstrike_pulumi/prevention_policy_precedence.py
crowdstrike_pulumi/prevention_policy_windows.py
crowdstrike_pulumi/provider.py
crowdstrike_pulumi/pulumi-plugin.json
crowdstrike_pulumi/py.typed
crowdstrike_pulumi/sensor_update_policy.py
crowdstrike_pulumi/sensor_update_policy_host_group_attachment.py
crowdstrike_pulumi/sensor_update_policy_precedence.py
crowdstrike_pulumi.egg-info/PKG-INFO
crowdstrike_pulumi.egg-info/SOURCES.txt
crowdstrike_pulumi.egg-info/dependency_links.txt
crowdstrike_pulumi.egg-info/not-zip-safe
crowdstrike_pulumi.egg-info/requires.txt
crowdstrike_pulumi.egg-info/top_level.txt
crowdstrike_pulumi/config/__init__.py
crowdstrike_pulumi/config/vars.py