Metadata-Version: 2.1
Name: crowdstrike-pulumi
Version: 0.0.14
Summary: A Pulumi package for creating and managing CrowdStrike resources
Home-page: https://crowdstrike.com
License: Apache-2.0
Project-URL: Repository, https://github.com/crowdstrike/pulumi-crowdstrike
Keywords: pulumi crowdstrike category/infrastructure
Platform: UNKNOWN
Requires-Python: >=3.9
